{"REQUEST_COMMON_FPKJ": {
		"NSRSBH": "110109500321654",
		"SBLX": "4",
		"SBBH": "",
		"FPQQLSH": "auto||time_str(%Y%m%d%H%M%S)||||readen_int(2)||",
		"KPZDDM": "",
		"FPLXDM": "026",
		"KPLX": "1",
		"BMB_BBH": "",
		"ZSFS": "0",
		"XSF_NSRSBH": "110109500321654",
		"XSF_MC": "百旺电子测试1",
		"XSF_DZDH": "地址市期以西南湖南路以期以西南湖南路以期123456049湖南路以期012065东北民谣呀东北民谣呀东北民谣呀12100",
		"XSF_YHZH": "银行市期以西南湖南路以期以西南湖南路以期123456049湖南路以期012A65东北民谣呀东北民谣呀东北民谣呀12100",
		"GMF_NSRSBH": "",
		"GMF_MC": "购买方期以西南湖南路以期以西南湖南路以期123456049湖南路以期012065东北民谣呀东北民谣呀东北民谣呀12100",
		"GMF_DZDH": "",
		"GMF_YHZH": "",
		"GMF_SJH": "",
		"GMF_DZYX": "zouxh@fapiao.com",
		"FPT_ZH": "",
		"WX_OPENID": "",
		"KPR": "开票人",
		"SKR": "",
		"FHR": "",
		"YFP_DM": "",
		"YFP_HM": "",
		"JSHJ": "-85",
		"HJJE": "-82.52",
		"HJSE": "-2.48",
		"KCE": "",
		"BZ": "",
		"BY1": "",
		"BY2": "",
		"BY3": "",
		"BY4": "",
		"BY5": "",
		"BY6": "",
		"BY7": "",
		"BY8": "",
		"BY9": "",
		"BY10": "",
		"WX_ORDER_ID": "",
		"WX_APP_ID": "",
		"ZFB_UID": "",
		"TSPZ": "",
		"QJ_ORDER_ID": "",
		"QDBZ": "",
		"TZDBH": "",
		"COMMON_FPKJ_XMXX": [
			{
				"FPHXZ": "0",
				"SPBM": "3040303019900000000",
				"ZXBM": "",
				"YHZCBS": "",
				"LSLBS": "",
				"ZZSTSGL": "",
				"XMMC": "*广告服务*服务费",
				"GGXH": "",
				"DW": "",
				"XMSL": "",
				"XMDJ": "",
				"XMJE": "-82.52",
				"SL": "0.03",
				"SE": "-2.48",
                "HSBZ": "",
				"BY1": "",
				"BY2": "",
				"BY3": "",
				"BY4": "",
				"BY5": ""
			}
		]
	},
	"CALLBACK_URL": "",
	"LSH": ""
}